conestrip/__init__.py
conestrip/cones.py
conestrip/conestrip_cdd.py
conestrip/conestrip_z3.py
conestrip/extended_cones.py
conestrip/gamble_algorithms.py
conestrip/global_settings.py
conestrip/optimization.py
conestrip/polyhedron.py
conestrip/prevision.py
conestrip/propositional_algorithms.py
conestrip/propositional_cones.py
conestrip/propositional_conestrip.py
conestrip/propositional_sentence_parser.py
conestrip/random_cones.py
conestrip/random_extended_cones.py
conestrip/sure_loss.py
conestrip/utility.py
CONEstrip-0.1.1.dist-info/LICENSE
CONEstrip-0.1.1.dist-info/METADATA
CONEstrip-0.1.1.dist-info/WHEEL
CONEstrip-0.1.1.dist-info/top_level.txt
CONEstrip-0.1.1.dist-info/RECORD
