Metadata-Version: 2.1
Name: CONEstrip
Version: 0.1.1
Summary: An implementation of the CONEstrip algorithms using python and z3.
Home-page: https://github.com/wiegerw/CONEstrip
Author: Wieger Wesselink
Author-email: j.w.wesselink@tue.nl
Project-URL: Bug Tracker, https://github.com/wiegerw/CONEstrip/issues
Classifier: Programming Language :: Python :: 3
Classifier: License :: OSI Approved :: Boost Software License 1.0 (BSL-1.0)
Classifier: Operating System :: OS Independent
Requires-Python: >=3.6
License-File: LICENSE
